{"expireTime":9007200874353572000,"key":"96e8830f015b4072cff7b7299bf266de","val":{"name":"IMAGE_PROCESSING","inputPaths":["/home/arun/Documents/SuperAgencyBlog/@elegantstack/education/content/authors/sarah-doe.png"],"outputDir":"/home/arun/Documents/SuperAgencyBlog/@elegantstack/education/public/static/87de5bfbd74cc446592cf783a2ed157f","args":{"isLazy":false,"operations":[{"outputPath":"46e60/sarah-doe.png","args":{"height":150,"width":150,"cropFocus":1,"toFormat":"png","quality":80,"fit":"cover"}},{"outputPath":"d612b/sarah-doe.png","args":{"height":300,"width":300,"cropFocus":1,"toFormat":"png","quality":80,"fit":"cover"}}],"pluginOptions":{"base64Width":20,"forceBase64Format":"","useMozJpeg":false,"stripMetadata":true,"lazyImageGeneration":true,"defaultQuality":75,"failOnError":true,"plugins":[]}}}}